stabledefaults/__init__.py
stabledefaults/decorator.py
stabledefaults-0.1.4.dist-info/METADATA
stabledefaults-0.1.4.dist-info/WHEEL
stabledefaults-0.1.4.dist-info/LICENSE
stabledefaults-0.1.4.dist-info/RECORD
