Metadata-Version: 2.1
Name: stabledefaults
Version: 0.1.4
Summary: Allows for mutable defaults comfortably and intuitively.
Home-page: https://github.com/AloizioMacedo/stabledefaults
Author: AloizioMacedo
Author-email: atsam2@hotmail.com
Requires-Python: >=3.8,<4.0
Classifier: Programming Language :: Python :: 3
Classifier: Programming Language :: Python :: 3.8
Classifier: Programming Language :: Python :: 3.9
Classifier: Programming Language :: Python :: 3.10
Classifier: Programming Language :: Python :: 3.11
Project-URL: Repository, https://github.com/AloizioMacedo/stabledefaults
